imtiaz_analysis/__init__.py
imtiaz_analysis/analyze.py
imtiazanalysis-0.1.0.dist-info/METADATA
imtiazanalysis-0.1.0.dist-info/WHEEL
imtiazanalysis-0.1.0.dist-info/top_level.txt
imtiazanalysis-0.1.0.dist-info/RECORD
