Metadata-Version: 2.4
Name: ImtiazAnalysis
Version: 0.1.0
Summary: An automated library for comprehensive data preprocessing and Exploratory Data Analysis (EDA).
Home-page: 
Author: Imtiaz (Your Name)
Author-email: imtiazkarachi6@gmail.com
Classifier: Programming Language :: Python :: 3
Classifier: License :: OSI Approved :: MIT License
Classifier: Operating System :: OS Independent
Classifier: Topic :: Scientific/Engineering :: Information Analysis
Requires-Python: >=3.6
Requires-Dist: pandas
Requires-Dist: numpy
Requires-Dist: matplotlib
Requires-Dist: seaborn
Requires-Dist: scikit-learn
Dynamic: author
Dynamic: author-email
Dynamic: classifier
Dynamic: description
Dynamic: description-content-type
Dynamic: requires-dist
Dynamic: requires-python
Dynamic: summary
